DjangoHtmlFiller/Inserter.py
DjangoHtmlFiller/OsScrawler.py
DjangoHtmlFiller/__init__.py
DjangoHtmlFiller-1.0.4.dist-info/LICENSE
DjangoHtmlFiller-1.0.4.dist-info/METADATA
DjangoHtmlFiller-1.0.4.dist-info/WHEEL
DjangoHtmlFiller-1.0.4.dist-info/top_level.txt
DjangoHtmlFiller-1.0.4.dist-info/RECORD
