Metadata-Version: 2.1
Name: DjangoHtmlFiller
Version: 1.0.4
Summary: This code is for those who are tired of inserting {% static ' ' %} in every href,src links in html files while creating a Django project.
Home-page: https://github.com/Jay206-Programmer/DjangoHtmlFiller
Author: Jay Shukla
Author-email: jayshukla0034@gmail.com
License: MIT
Platform: UNKNOWN
Classifier: License :: OSI Approved :: MIT License
Classifier: Programming Language :: Python :: 3
Classifier: Programming Language :: Python :: 3.7
